mbs/__init__.py
mbs/__main__.py
mbs/manager.py
mbs/blogs/__init__.py
mbs/blogs/cnblogs.py
mbs/blogs/jianshu.py
mbs/blogs/segmentfault.py
mbs/blogs/site.py
mbs/utils/__init__.py
mbs/utils/common.py
mbs/utils/database.py
mbs/utils/exceptions.py
mbs/utils/logger.py
mbs/utils/settings.py
mbs/utils/structs/__init__.py
mbs/utils/structs/jianshu.py
mbs/utils/structs/meta_weblog.py
mbs_cn-0.0.7.dist-info/LICENSE
mbs_cn-0.0.7.dist-info/METADATA
mbs_cn-0.0.7.dist-info/WHEEL
mbs_cn-0.0.7.dist-info/entry_points.txt
mbs_cn-0.0.7.dist-info/top_level.txt
mbs_cn-0.0.7.dist-info/RECORD
