Metadata-Version: 2.1
Name: mbs-cn
Version: 0.0.7
Summary: 
Home-page: https://github.com/thep0y/mbs
Author: thepoy
Author-email: thepoy@163.com
License: MIT
Keywords: blog 博客 博客园 简书
Platform: UNKNOWN
Requires-Dist: requests
Requires-Dist: colorful-logger
